hyd/HaukursYouTubeDownloader.py
hyd-0.1.7.dist-info/LICENSE
hyd-0.1.7.dist-info/METADATA
hyd-0.1.7.dist-info/WHEEL
hyd-0.1.7.dist-info/entry_points.txt
hyd-0.1.7.dist-info/RECORD
